{
  "english": "Eighth",
  "hebrew": "שמיני",
  "transliteration": "Shemini | שמיני",
  "week": 26,
  "title": "Bible Study for Week 26",
  "intro": {
    "summary": "Learn the Bible in 52 weeks. This study covers Jacob's journey, his vision at Bethel, and the covenant events shaping Israel's future...",
    "instructions": "How it works: Read daily, listen to audio, and meet weekly in your HomeGroup."
  },
  "sections": {
    "audio_playlist": [
      {
        "label": "Torah",
        "src": "http://audio.esvbible.org/hw/03009001-03011047.mp3",
        "heb": "https://mechon-mamre.org/mp3/t0521.mp3",
        "grk": "https://info2.sermon-online.com/greek/Bible/Greek-Audio_Bible_Complete_Old_Testament_OT_MP3.mp3"
      },
      {
        "label": "Prophets",
        "src": "http://audio.esvbible.org/hw/40017001-40017027.mp3",
        "heb": "https://mechon-mamre.org/mp3/t0521.mp3",
        "grk": "https://info2.sermon-online.com/greek/Bible/Greek-Audio_Bible_Complete_Old_Testament_OT_MP3.mp3"
      },
      {
        "label": "Gospels",
        "src": "http://audio.esvbible.org/hw/41009001-41009013.mp3",
        "heb": "https://mechon-mamre.org/mp3/t0521.mp3",
        "grk": "https://info2.sermon-online.com/greek/Bible/Greek-Audio_Bible_Complete_Old_Testament_OT_MP3.mp3"
      },
      {
        "label": "Letters",
        "src": "http://audio.esvbible.org/hw/59001001-59001027.mp3",
        "heb": "https://mechon-mamre.org/mp3/t0521.mp3",
        "grk": "https://info2.sermon-online.com/greek/Bible/Greek-Audio_Bible_Complete_Old_Testament_OT_MP3.mp3"
      }
    ],
    "chapter_outlines": {
      "Torah": [
        "Leviticus 9:1 | Aaron's Priesthood Inaugurated",
        "Leviticus 10:1 | Nadab and Abihu",
        "Leviticus 11:1 | Clean and Unclean Foods"
        "Leviticus 11:24 | Unclean Animals"
      ],
      "Prophets": [
        "2 Samuel 7:1 | God's Covenant with David",
        "Ezekiel 36:1-38 | Comfort to the Land of Israel, and restoring the house of Israel (all 10 tribes, not the house of Judah)"
      ],
      "Writings": [],
      "Gospels": [
        "Mark 9:1-13| The resurrection of Jesus prophesied by His own words"
      ],
      "Letters": [
        "Acts 15:1 | Some said you cannot be saved without circumsision."
      ],
      "Revelation": []
    },
    "commentary": {
      "quote": "There are few ideal families in the Bible. Jacob's certainly wasn't…",
      "content": "Jacob's story reveals the struggle between flesh and spirit, and how God redeems broken circumstances through covenant promises..."
    },
    "deeper_learning": "Explore the prophetic connections between Jacob's ladder and the Temple Mount. This passage unveils YHVH's sovereignty beyond time and space...",
    "aleph_tav": "Key occurrences of את reveal divine fingerprints in the text, marking significant covenantal moments...",
    "kids_study": {
      "videos": [
        "https://www.youtube.com/embed/lre-LLz-UzE",
        "https://www.youtube.com/embed/YzjHjXe-2XU"
      ],
      "pdf": "COLORING_PAGES.pdf"
    },
    "language_learning": {
      "hebrew": {
        "word": "Makom",
        "text": "מקום",
        "meaning": "The Place"
      },
      "greek": {
        "word": "Pistis",
        "text": "πίστις",
        "meaning": "Faith"
      },
      "audio": "YOUR-TEACHING-LINK.mp3"
    },
    "psalms_plan": [
      {
        "day": "Sunday",
        "audio": "https://audio.esv.org/hw/mq/19001001-19029011.mp3"
      },
      {
        "day": "Monday",
        "audio": "https://audio.esv.org/hw/mq/19030001-19050023.mp3"
      },
      {
        "day": "Tuesday",
        "audio": "https://audio.esv.org/hw/mq/19051001-19072020.mp3"
      }
    ]
  },
  "first_verse": {
    "text": "Insert first verse text here...",
    "reference": "Book Chapter:Verse"
  },
  "subtitle": "Shemini | שמיני"
}